makegen/__init__.py
makegen/__main__.py
makegen/main.py
makegen-0.1.1.dist-info/LICENSE
makegen-0.1.1.dist-info/METADATA
makegen-0.1.1.dist-info/WHEEL
makegen-0.1.1.dist-info/RECORD
